pushgateway_client/__init__.py
pushgateway_client/client.py
pushgateway_client-0.0.12.dist-info/LICENSE
pushgateway_client-0.0.12.dist-info/METADATA
pushgateway_client-0.0.12.dist-info/WHEEL
pushgateway_client-0.0.12.dist-info/top_level.txt
pushgateway_client-0.0.12.dist-info/RECORD
