Metadata-Version: 2.1
Name: pushgateway_client
Version: 0.0.12
Summary: Python3专用的pushgateway客户端，可以向Pushgateway中推送指标数据，支持多标签设定
Home-page: https://blog.taycc.com/pages/opensource/pushgateway_client.html
Author: Tay
Author-email: tay3223@qq.com
License: UNKNOWN
Project-URL: 使用文档, https://blog.taycc.com/pages/opensource/pushgateway_client.html
Platform: UNKNOWN
Classifier: Programming Language :: Python :: 3
Classifier: License :: OSI Approved :: MIT License
Classifier: Operating System :: OS Independent
Requires-Python: >=3.6
License-File: LICENSE
